litestar_asyncpg/__init__.py
litestar_asyncpg/__metadata__.py
litestar_asyncpg/_utils.py
litestar_asyncpg/config.py
litestar_asyncpg/plugin.py
litestar_asyncpg/py.typed
litestar_asyncpg-0.5.0.dist-info/METADATA
litestar_asyncpg-0.5.0.dist-info/WHEEL
litestar_asyncpg-0.5.0.dist-info/licenses/LICENSE
litestar_asyncpg-0.5.0.dist-info/RECORD
