Metadata-Version: 2.4
Name: litestar-asyncpg
Version: 0.5.0
Summary: Asyncpg plugin for Litestar
Project-URL: Changelog, https://litestar-org.github.io/litesatr-asyncpg/latest/changelog
Project-URL: Discord, https://discord.gg/X3FJqy8d2j
Project-URL: Documentation, https://litestar-org.github.io/litesatr-asyncpg/latest/
Project-URL: Homepage, https://litestar-org.github.io/litesatr-asyncpg/latest/
Project-URL: Issue, https://github.com/litestar-org/litestar-asyncpg/issues/
Project-URL: Source, https://github.com/litestar-org/litestar-asyncpg
Author-email: Cody Fincher <cody@litestar.dev>
License: MIT
License-File: LICENSE
Keywords: asyncpg,litestar
Classifier: Development Status :: 3 - Alpha
Classifier: Environment :: Web Environment
Classifier: Intended Audience :: Developers
Classifier: Intended Audience :: System Administrators
Classifier: License :: OSI Approved :: MIT License
Classifier: Natural Language :: English
Classifier: Operating System :: OS Independent
Classifier: Programming Language :: Python
Classifier: Programming Language :: Python :: 3.9
Classifier: Programming Language :: Python :: 3.10
Classifier: Programming Language :: Python :: 3.11
Classifier: Programming Language :: Python :: 3.12
Classifier: Programming Language :: Python :: 3.13
Classifier: Topic :: Database
Classifier: Topic :: Database :: Database Engines/Servers
Classifier: Topic :: Software Development
Classifier: Typing :: Typed
Requires-Python: >=3.9
Requires-Dist: asyncpg>=0.28.0
Requires-Dist: litestar>=2.0.29
Requires-Dist: typing-extensions
